neuro_deloy.py
quicksample.py
neuro_deloy-0.0.1.dist-info/METADATA
neuro_deloy-0.0.1.dist-info/WHEEL
neuro_deloy-0.0.1.dist-info/top_level.txt
neuro_deloy-0.0.1.dist-info/RECORD
